eagle_exporter/cli.py
eagle_exporter/core.py
eagle_exporter-0.1.4.dist-info/entry_points.txt
eagle_exporter-0.1.4.dist-info/LICENSE
eagle_exporter-0.1.4.dist-info/METADATA
eagle_exporter-0.1.4.dist-info/WHEEL
eagle_exporter-0.1.4.dist-info/RECORD
