Metadata-Version: 2.3
Name: eagle-exporter
Version: 0.1.4
Summary: CLI tool and library for exporting metadata from Eagle app JSON into parquet or huggingface dataset.
License: MIT
Author: yada
Author-email: trojblue@gmail.com
Requires-Python: >=3.10,<4.0
Classifier: License :: OSI Approved :: MIT License
Classifier: Programming Language :: Python :: 3
Classifier: Programming Language :: Python :: 3.10
Classifier: Programming Language :: Python :: 3.11
Classifier: Programming Language :: Python :: 3.12
Classifier: Programming Language :: Python :: 3.13
Requires-Dist: click (>=8.1.8,<9.0.0)
Requires-Dist: datasets (>=3.2.0,<4.0.0)
Requires-Dist: pandas (>=2.2.3,<3.0.0)
Requires-Dist: pillow
Requires-Dist: tqdm (>=4.67.1,<5.0.0)
Requires-Dist: unibox (>=0.8.2,<0.9.0)
